mltome/__init__.py
mltome/cometml.py
mltome/neptune.py
mltome/skorch/__init__.py
mltome/skorch/callbacks.py
mltome/skorch/lr_finder.py
mltome-0.1.0.post1.dist-info/LICENSE
mltome-0.1.0.post1.dist-info/METADATA
mltome-0.1.0.post1.dist-info/WHEEL
mltome-0.1.0.post1.dist-info/top_level.txt
mltome-0.1.0.post1.dist-info/RECORD
